shap/__init__.py
shap/tree_shap.h
shap/_cext.cpython-311-x86_64-linux-gnu.so
shap/datasets.py
shap/common.py
shap/plots/__init__.py
shap/plots/colors.py
shap/plots/embedding.py
shap/plots/image.py
shap/plots/summary.py
shap/plots/dependence.py
shap/plots/force.py
shap/plots/force_matplotlib.py
shap/plots/monitoring.py
shap/plots/resources/logoSmallGray.png
shap/plots/resources/bundle.js
shap/explainers/kernel.py
shap/explainers/__init__.py
shap/explainers/tree.py
shap/explainers/pytree.py
shap/explainers/linear.py
shap/explainers/mimic.py
shap/explainers/sampling.py
shap/explainers/gradient.py
shap/explainers/explainer.py
shap/explainers/other/__init__.py
shap/explainers/other/coefficent.py
shap/explainers/other/random.py
shap/explainers/other/treegain.py
shap/explainers/other/lime.py
shap/explainers/deep/__init__.py
shap/explainers/deep/misc.py
shap/explainers/deep/deep_tf.py
shap/explainers/deep/deep_pytorch.py
shap/benchmark/__init__.py
shap/benchmark/measures.py
shap/benchmark/metrics.py
shap/benchmark/experiments.py
shap/benchmark/plots.py
shap/benchmark/methods.py
shap/benchmark/models.py
kundajelab_shap-1.dist-info/top_level.txt
kundajelab_shap-1.dist-info/METADATA
kundajelab_shap-1.dist-info/WHEEL
kundajelab_shap-1.dist-info/LICENSE
kundajelab_shap-1.dist-info/RECORD
